tes_chp/__init__.py
tes_chp/chp_subsystem.py
tes_chp-0.2.1.dist-info/METADATA
tes_chp-0.2.1.dist-info/WHEEL
tes_chp-0.2.1.dist-info/top_level.txt
tes_chp-0.2.1.dist-info/RECORD
