Metadata-Version: 2.2
Name: tes-chp
Version: 0.2.1
Summary: CHP models implemented in tespy (for WWNW)
Classifier: Programming Language :: Python
Classifier: Programming Language :: Python :: 3
Classifier: Programming Language :: Python :: 3.10
Classifier: Programming Language :: Python :: 3.11
Classifier: Programming Language :: Python :: 3.12
Classifier: Programming Language :: Python :: 3.13
Classifier: Programming Language :: Python :: Implementation :: CPython
Classifier: Programming Language :: Python :: Implementation :: PyPy
Requires-Python: >=3.10
Requires-Dist: tespy>=0.7.9
Requires-Dist: numpy>=2.0.0
Requires-Dist: pandas>=2.0.0
